fastapi_passwordless/__init__.py
fastapi_passwordless-0.0.5.dist-info/LICENSE
fastapi_passwordless-0.0.5.dist-info/WHEEL
fastapi_passwordless-0.0.5.dist-info/METADATA
fastapi_passwordless-0.0.5.dist-info/RECORD
